setup.py
yunti/__init__.py
yunti/__main__.py
yunti/consts.py
yunti/ping.py
yunti.egg-info/PKG-INFO
yunti.egg-info/SOURCES.txt
yunti.egg-info/dependency_links.txt
yunti.egg-info/top_level.txt