Metadata-Version: 1.0
Name: yunti
Version: 0.0.3
Summary: python -m yunti
Home-page: UNKNOWN
Author: gonjay
Author-email: me@gonjay.com
License: MIT License
Keywords: yunti,vpn
Platform: any
